odoo8_addon_contract_recurring_plans-8.0.1.0.0.99.dev16-py3.8-nspkg.pth
odoo_addons/contract_recurring_plans/README.rst
odoo_addons/contract_recurring_plans/__init__.py
odoo_addons/contract_recurring_plans/__openerp__.py
odoo_addons/contract_recurring_plans/i18n/ca.po
odoo_addons/contract_recurring_plans/i18n/contract_recurring_plans.pot
odoo_addons/contract_recurring_plans/i18n/de.po
odoo_addons/contract_recurring_plans/i18n/el_GR.po
odoo_addons/contract_recurring_plans/i18n/es.po
odoo_addons/contract_recurring_plans/i18n/es_MX.po
odoo_addons/contract_recurring_plans/i18n/fi.po
odoo_addons/contract_recurring_plans/i18n/fr.po
odoo_addons/contract_recurring_plans/i18n/pt_BR.po
odoo_addons/contract_recurring_plans/i18n/sk_SK.po
odoo_addons/contract_recurring_plans/i18n/sl.po
odoo_addons/contract_recurring_plans/i18n/zh_CN.po
odoo_addons/contract_recurring_plans/models/__init__.py
odoo_addons/contract_recurring_plans/models/account_analytic_invoice_line.py
odoo_addons/contract_recurring_plans/static/description/icon.png
odoo_addons/contract_recurring_plans/static/description/icon.svg
odoo_addons/contract_recurring_plans/tests/__init__.py
odoo_addons/contract_recurring_plans/tests/test_contract_recurring_plans.py
odoo_addons/contract_recurring_plans/views/account_analytic_invoice_line_view.xml
odoo8_addon_contract_recurring_plans-8.0.1.0.0.99.dev16.dist-info/METADATA
odoo8_addon_contract_recurring_plans-8.0.1.0.0.99.dev16.dist-info/WHEEL
odoo8_addon_contract_recurring_plans-8.0.1.0.0.99.dev16.dist-info/namespace_packages.txt
odoo8_addon_contract_recurring_plans-8.0.1.0.0.99.dev16.dist-info/top_level.txt
odoo8_addon_contract_recurring_plans-8.0.1.0.0.99.dev16.dist-info/RECORD
